patchly/__init__.py
patchly/aggregator.py
patchly/array_like.py
patchly/sampler.py
patchly/slicer.py
patchly/utils.py
patchly-0.1.dist-info/METADATA
patchly-0.1.dist-info/WHEEL
patchly-0.1.dist-info/top_level.txt
patchly-0.1.dist-info/RECORD
